mlmodule/__init__.py
mlmodule/hyperparameter_tuning.py
mlmodule/model_selection.py
mlmodule/model_training.py
MLmodule-0.0.2.dist-info/METADATA
MLmodule-0.0.2.dist-info/WHEEL
MLmodule-0.0.2.dist-info/top_level.txt
MLmodule-0.0.2.dist-info/RECORD
