Metadata-Version: 2.1
Name: MLmodule
Version: 0.0.2
Summary: Alchmey Cloud's compiled machine learning module
Home-page: UNKNOWN
Author: Ana Belisario
Author-email: ana.belisario@alchemy.cloud
License: UNKNOWN
Keywords: automated machine learning
Platform: UNKNOWN
Classifier: Development Status :: 3 - Alpha
Classifier: Topic :: Scientific/Engineering :: Physics
Classifier: Intended Audience :: Developers
Classifier: Programming Language :: Python :: 3.8
Requires-Dist: numpy
Requires-Dist: pandas
Requires-Dist: scikit-learn
Requires-Dist: scipy
Requires-Dist: xgboost
